pipfile_cli/__init__.py
pipfile_cli/__main__.py
pipfile_cli/version.txt
pipfile_cli/vendor/README.txt
pipfile_cli/vendor/__init__.py
pipfile_cli/vendor/pipfile/LICENSE
pipfile_cli/vendor/pipfile/LICENSE.APACHE
pipfile_cli/vendor/pipfile/LICENSE.BSD
pipfile_cli/vendor/pipfile/__about__.py
pipfile_cli/vendor/pipfile/__init__.py
pipfile_cli/vendor/pipfile/api.py
pipfile_cli-1.0.0.dev4.dist-info/METADATA
pipfile_cli-1.0.0.dev4.dist-info/RECORD
pipfile_cli-1.0.0.dev4.dist-info/WHEEL
pipfile_cli-1.0.0.dev4.dist-info/entry_points.txt
pipfile_cli-1.0.0.dev4.dist-info/top_level.txt
