Metadata-Version: 2.1
Name: pipfile-cli
Version: 1.0.0.dev4
Summary: Command line interface around Pipfile operations
Home-page: https://github.com/sarugaku/pipfile-cli
Author: Tzu-ping Chung
Author-email: uranusjr@gmail.com
License: ISC License
Keywords: pipenv,pipfile
Platform: UNKNOWN
Classifier: Development Status :: 2 - Pre-Alpha
Classifier: Environment :: Console
Classifier: Intended Audience :: Developers
Classifier: License :: OSI Approved :: ISC License (ISCL)
Classifier: Operating System :: OS Independent
Classifier: Programming Language :: Python :: 3 :: Only
Classifier: Programming Language :: Python :: 3.6
Classifier: Topic :: Software Development :: Libraries :: Python Modules
Requires-Python: >= '3.6'
Requires-Dist: click
Requires-Dist: requirementslib
Requires-Dist: toml
